<?xml version="1.0" encoding="UTF-8"?>
<site>
   <description name="The SiLift UpdateSite" url="http://pi.informatik.uni-siegen.de/Projekte/SiLift/updatesite">
      This is the Eclipse IDE UpdateSite for the SiLift Tools.
   </description>
   <feature url="features/org.silift.tools.rulebaseeditor_0.1.0.201402221055.jar" id="org.silift.tools.rulebaseeditor" version="0.1.0.201402221055">
      <category name="SiLift Development Tools"/>
   </feature>
   <feature url="features/org.silift.matchers.emfcompare_0.1.0.201402221055.jar" id="org.silift.matchers.emfcompare" version="0.1.0.201402221055">
      <category name="SiLift Matchers"/>
   </feature>
   <feature url="features/org.silift.matchers.namedelement_0.1.0.201402221055.jar" id="org.silift.matchers.namedelement" version="0.1.0.201402221055">
      <category name="SiLift Matchers"/>
   </feature>
   <feature url="features/org.silift.matchers.uri_0.1.0.201402221055.jar" id="org.silift.matchers.uri" version="0.1.0.201402221055">
      <category name="SiLift Matchers"/>
   </feature>
   <feature url="features/org.silift.matchers.uuid_0.1.0.201402221055.jar" id="org.silift.matchers.uuid" version="0.1.0.201402221055">
      <category name="SiLift Matchers"/>
   </feature>
   <feature url="features/org.silift.domains.ecore_0.1.0.201402221055.jar" id="org.silift.domains.ecore" version="0.1.0.201402221055">
      <category name="SiLift Domains"/>
   </feature>
   <feature url="features/org.silift.domains.fm_0.1.0.201402221055.jar" id="org.silift.domains.fm" version="0.1.0.201402221055">
      <category name="SiLift Domains"/>
   </feature>
   <feature url="features/org.silift.compare_0.1.0.201402221055.jar" id="org.silift.compare" version="0.1.0.201402221055">
      <category name="SiLift"/>
   </feature>
   <feature url="features/org.silift.core_0.1.0.201402221055.jar" id="org.silift.core" version="0.1.0.201402221055">
      <category name="SiLift"/>
   </feature>
   <feature url="features/org.silift.henshin.extensions_0.1.0.201402221055.jar" id="org.silift.henshin.extensions" version="0.1.0.201402221055" patch="true">
      <category name="SiLift"/>
   </feature>
   <feature url="features/org.silift.merging_0.1.0.201402221055.jar" id="org.silift.merging" version="0.1.0.201402221055">
      <category name="SiLift"/>
   </feature>
   <feature url="features/org.silift.patching_0.1.0.201402221055.jar" id="org.silift.patching" version="0.1.0.201402221055">
      <category name="SiLift"/>
   </feature>
   <category-def name="SiLift" label="SiLift">
      <description>
         The SiLift tool plugins / features
      </description>
   </category-def>
   <category-def name="SiLift Domains" label="SiLift Domains">
      <description>
         The SiLift domain specific plugins
      </description>
   </category-def>
   <category-def name="SiLift Matchers" label="SiLift Matchers">
      <description>
         The SiLift Matchers and Matching Adapters
      </description>
   </category-def>
   <category-def name="SiLift Development Tools" label="SiLift Development Tools">
      <description>
         The SiLift tools for development
      </description>
   </category-def>
</site>
